{"version":1,"resource":"vscode-remote://freecodecam-learnworldc-7v8vfimdzfd.ws-us110.gitpod.io/workspace/project/queries.sh","entries":[{"id":"wxwu.sh","timestamp":1711605234450},{"id":"blLY.sh","timestamp":1711606103441},{"id":"hajO.sh","timestamp":1711606989593},{"id":"b6V4.sh","timestamp":1711607017157},{"id":"v3vY.sh","timestamp":1711607053677},{"id":"0kEm.sh","timestamp":1711607074565},{"id":"0VYv.sh","timestamp":1711607102101},{"id":"O3dz.sh","timestamp":1711607178273},{"id":"OE68.sh","timestamp":1711607189065},{"id":"6VP8.sh","timestamp":1711607276597},{"id":"o0db.sh","source":"undoRedo.source","timestamp":1711607283245},{"id":"FxJ6.sh","timestamp":1711607321133},{"id":"qRoR.sh","source":"undoRedo.source","timestamp":1711607334345}]}